{
  "backend": {
    "loaded_checkpoint": "yolo26m-pose.pt",
    "is_engine": false,
    "imgsz": 640,
    "conf": 0.25,
    "max_det": 8,
    "tracker": "bytetrack.yaml"
  },
  "capture_profile": {
    "source": "2",
    "backend": "V4L2",
    "width": 640,
    "height": 480,
    "fps": 30.0,
    "buffersize_req": 1,
    "fourcc": 1448695129
  },
  "capture_dropped": 27,
  "recorder_dropped": 0,
  "frames": 42,
  "emitted": 39,
  "lat_sw_ms": {
    "p50": 31.665,
    "p95": 33.443,
    "p99": 34.161,
    "mean": 31.850589743589744,
    "n": 39
  },
  "jitter_ms": {
    "p50": 0.097,
    "p95": 1.394,
    "p99": 1.64,
    "mean": 0.2522894736842105,
    "n": 38
  },
  "stream_id": "557964d7efa62b0b",
  "contract_id": "82c51ab25ce36876c982a6afb19e5cf7",
  "focused_slot": 0,
  "focus_mode": "auto"
}